khalil_zaidi_calculator/__init__.py
khalil_zaidi_calculator/calculator.py
khalil_zaidi_calculator-0.1.0.dist-info/licenses/LICENSE
khalil_zaidi_calculator-0.1.0.dist-info/METADATA
khalil_zaidi_calculator-0.1.0.dist-info/WHEEL
khalil_zaidi_calculator-0.1.0.dist-info/top_level.txt
khalil_zaidi_calculator-0.1.0.dist-info/RECORD
