Metadata-Version: 2.4
Name: khalil-zaidi-calculator
Version: 0.1.0
Summary: Advanced calculator with extra math operations
Home-page: https://github.com/yourusername/khalil-zaidi-calculator
Author: خليل الزايدي
Author-email: your_email@example.com
Classifier: Programming Language :: Python :: 3
Classifier: License :: OSI Approved :: MIT License
Classifier: Operating System :: OS Independent
Requires-Python: >=3.6
License-File: LICENSE
Dynamic: author
Dynamic: author-email
Dynamic: classifier
Dynamic: description
Dynamic: description-content-type
Dynamic: home-page
Dynamic: license-file
Dynamic: requires-python
Dynamic: summary
